simple_log/__init__.py
simple_log/admin.py
simple_log/apps.py
simple_log/conf.py
simple_log/fields.py
simple_log/models.py
simple_log/signals.py
simple_log/utils.py
simple_log/locale/en/LC_MESSAGES/django.mo
simple_log/locale/en/LC_MESSAGES/django.po
simple_log/locale/ru/LC_MESSAGES/django.mo
simple_log/locale/ru/LC_MESSAGES/django.po
simple_log/management/__init__.py
simple_log/management/commands/__init__.py
simple_log/management/commands/view_tracking_models.py
simple_log/migrations/0001_initial.py
simple_log/migrations/0002_simplelog_related_logs.py
simple_log/migrations/0003_auto_20171002_1318.py
simple_log/migrations/0004_auto_20180614_0727.py
simple_log/migrations/__init__.py
simple_log/templates/simple_log/admin/change_list.html
simple_log/templates/simple_log/admin/changes_table.html
simple_log/templates/simple_log/admin/detail.html
simple_log/templates/simple_log/admin/field_value.html
simple_log/templates/simple_log/admin/history_change_list.html
simple_log/templatetags/__init__.py
simple_log/templatetags/simple_log_tags.py
django_simple_log-0.4.0.dist-info/LICENSE
django_simple_log-0.4.0.dist-info/METADATA
django_simple_log-0.4.0.dist-info/WHEEL
django_simple_log-0.4.0.dist-info/top_level.txt
django_simple_log-0.4.0.dist-info/RECORD
