Metadata-Version: 2.1
Name: django-simple-log
Version: 0.4.0
Summary: Logging django models changes.
Home-page: https://github.com/kindlycat/django-simple-log/
Author: Grigory Mishchenko
Author-email: grishkokot@gmail.com
Keywords: django,log,audit,history
Classifier: Programming Language :: Python :: 2.7
Classifier: Programming Language :: Python :: 3.4
Classifier: Programming Language :: Python :: 3.5
Classifier: Programming Language :: Python :: 3.6
Classifier: Programming Language :: Python :: 3.7
Classifier: Framework :: Django :: 1.11
Classifier: Framework :: Django :: 2.0
Classifier: Framework :: Django :: 2.1
Classifier: License :: OSI Approved :: BSD License
License-File: LICENSE
Requires-Dist: Django >=1.11
Requires-Dist: django-request-vars >=1.0.1
